chatlas/__init__.py
chatlas/_auto.py
chatlas/_batch_chat.py
chatlas/_batch_job.py
chatlas/_callbacks.py
chatlas/_chat.py
chatlas/_content.py
chatlas/_content_expand.py
chatlas/_content_image.py
chatlas/_content_pdf.py
chatlas/_display.py
chatlas/_inspect.py
chatlas/_interpolate.py
chatlas/_live_render.py
chatlas/_logging.py
chatlas/_mcp_manager.py
chatlas/_merge.py
chatlas/_parallel.py
chatlas/_progress.py
chatlas/_provider.py
chatlas/_provider_anthropic.py
chatlas/_provider_cloudflare.py
chatlas/_provider_databricks.py
chatlas/_provider_deepseek.py
chatlas/_provider_github.py
chatlas/_provider_google.py
chatlas/_provider_groq.py
chatlas/_provider_huggingface.py
chatlas/_provider_mistral.py
chatlas/_provider_ollama.py
chatlas/_provider_openai.py
chatlas/_provider_openai_azure.py
chatlas/_provider_openai_completions.py
chatlas/_provider_openai_generic.py
chatlas/_provider_openrouter.py
chatlas/_provider_perplexity.py
chatlas/_provider_portkey.py
chatlas/_provider_snowflake.py
chatlas/_repr.py
chatlas/_tokens.py
chatlas/_tokens_old.py
chatlas/_tools.py
chatlas/_tools_builtin.py
chatlas/_turn.py
chatlas/_typing_extensions.py
chatlas/_utils.py
chatlas/_version.py
chatlas/py.typed
chatlas/data/prices.json
chatlas/types/__init__.py
chatlas/types/anthropic/__init__.py
chatlas/types/anthropic/_client.py
chatlas/types/anthropic/_client_bedrock.py
chatlas/types/anthropic/_submit.py
chatlas/types/google/__init__.py
chatlas/types/google/_client.py
chatlas/types/google/_submit.py
chatlas/types/openai/__init__.py
chatlas/types/openai/_client.py
chatlas/types/openai/_client_azure.py
chatlas/types/openai/_submit.py
chatlas/types/openai/_submit_responses.py
chatlas-0.15.0.dist-info/METADATA
chatlas-0.15.0.dist-info/WHEEL
chatlas-0.15.0.dist-info/licenses/LICENSE
chatlas-0.15.0.dist-info/RECORD
