Metadata-Version: 2.4
Name: chatlas
Version: 0.15.0
Summary: A simple and consistent interface for chatting with LLMs
Project-URL: Homepage, https://posit-dev.github.io/chatlas
Project-URL: Documentation, https://posit-dev.github.io/chatlas
Project-URL: Repository, https://github.com/posit-dev/chatlas
Project-URL: Issues, https://github.com/posit-dev/chatlas/issues/
Project-URL: Changelog, https://github.com/posit-dev/chatlas/blob/main/CHANGELOG.md
Author-email: Carson Sievert <carson@posit.co>
License-Expression: MIT
License-File: LICENSE
Classifier: Development Status :: 4 - Beta
Classifier: Intended Audience :: Developers
Classifier: License :: OSI Approved :: MIT License
Classifier: Programming Language :: Python :: 3.10
Classifier: Programming Language :: Python :: 3.11
Classifier: Programming Language :: Python :: 3.12
Classifier: Programming Language :: Python :: 3.13
Classifier: Programming Language :: Python :: 3.14
Requires-Python: >=3.9
Requires-Dist: jinja2
Requires-Dist: openai
Requires-Dist: orjson
Requires-Dist: pydantic>=2.0
Requires-Dist: requests
Requires-Dist: rich
Provides-Extra: anthropic
Requires-Dist: anthropic; extra == 'anthropic'
Provides-Extra: azure-openai
Provides-Extra: bedrock-anthropic
Requires-Dist: anthropic[bedrock]; extra == 'bedrock-anthropic'
Provides-Extra: databricks
Requires-Dist: databricks-sdk; extra == 'databricks'
Provides-Extra: dev
Requires-Dist: anthropic[bedrock]; extra == 'dev'
Requires-Dist: databricks-sdk; extra == 'dev'
Requires-Dist: google-genai>=1.14.0; extra == 'dev'
Requires-Dist: htmltools; extra == 'dev'
Requires-Dist: matplotlib; extra == 'dev'
Requires-Dist: narwhals; extra == 'dev'
Requires-Dist: numpy>1.24.4; extra == 'dev'
Requires-Dist: openai; extra == 'dev'
Requires-Dist: pandas; extra == 'dev'
Requires-Dist: pillow; extra == 'dev'
Requires-Dist: polars; extra == 'dev'
Requires-Dist: python-dotenv; extra == 'dev'
Requires-Dist: ruff>=0.6.5; extra == 'dev'
Requires-Dist: shiny; extra == 'dev'
Requires-Dist: shinychat; extra == 'dev'
Requires-Dist: snowflake-ml-python>=1.8.4; extra == 'dev'
Requires-Dist: tenacity; extra == 'dev'
Requires-Dist: tiktoken; extra == 'dev'
Requires-Dist: torch; (python_version <= '3.11') and extra == 'dev'
Provides-Extra: docs
Requires-Dist: griffe>=1; extra == 'docs'
Requires-Dist: ipykernel; extra == 'docs'
Requires-Dist: ipywidgets; extra == 'docs'
Requires-Dist: nbclient; extra == 'docs'
Requires-Dist: nbformat; extra == 'docs'
Requires-Dist: numpy; extra == 'docs'
Requires-Dist: pandas; extra == 'docs'
Requires-Dist: pyyaml; extra == 'docs'
Requires-Dist: quartodoc>=0.7; extra == 'docs'
Requires-Dist: sentence-transformers; extra == 'docs'
Provides-Extra: eval
Requires-Dist: inspect-ai; (python_version >= '3.10') and extra == 'eval'
Provides-Extra: github
Provides-Extra: google
Requires-Dist: google-genai>=1.14.0; extra == 'google'
Provides-Extra: groq
Provides-Extra: mcp
Requires-Dist: mcp>=1.4.0; (python_version >= '3.10') and extra == 'mcp'
Provides-Extra: ollama
Provides-Extra: openai
Provides-Extra: perplexity
Provides-Extra: snowflake
Requires-Dist: snowflake-ml-python<=1.9.0; extra == 'snowflake'
Provides-Extra: test
Requires-Dist: pyright>=1.1.379; extra == 'test'
Requires-Dist: pytest-asyncio; extra == 'test'
Requires-Dist: pytest-recording>=0.13; extra == 'test'
Requires-Dist: pytest>=8.3.2; extra == 'test'
Requires-Dist: syrupy>=4; extra == 'test'
Requires-Dist: vcrpy>=6.0.0; extra == 'test'
Provides-Extra: vertex
Requires-Dist: google-genai>=1.14.0; extra == 'vertex'
